beekeeper/__init__.py
beekeeper/api.py
beekeeper/comms.py
beekeeper/data_handlers.py
beekeeper/exceptions.py
beekeeper/hive.py
beekeeper/variable_handlers.py
beekeeper/variables.py
beekeeper_alt-2022.9.3.dist-info/WHEEL
beekeeper_alt-2022.9.3.dist-info/METADATA
beekeeper_alt-2022.9.3.dist-info/RECORD
