Metadata-Version: 2.1
Name: beekeeper-alt
Version: 2022.9.3
Summary: beekeeper is a Python library designed around dynamically generating a RESTful client interface based on a minimal JSON hive
Home-page: https://github.com/miigotu/beekeeper
License: MIT
Keywords: REST,API,web,client,wrapper
Author: Jesse Shapiro
Author-email: jesse@bedrockdata.com
Maintainer: Dustyn Gibson
Maintainer-email: miigotu@gmail.com
Requires-Python: >=3.7.2,<4
Classifier: Development Status :: 4 - Beta
Classifier: Intended Audience :: Developers
Classifier: Intended Audience :: Information Technology
Classifier: Intended Audience :: System Administrators
Classifier: License :: OSI Approved :: MIT License
Classifier: Operating System :: OS Independent
Classifier: Programming Language :: Python
Classifier: Programming Language :: Python :: 3
Classifier: Programming Language :: Python :: 3.8
Classifier: Programming Language :: Python :: 3.9
Classifier: Programming Language :: Python :: 3.10
Classifier: Programming Language :: Python :: 3
Classifier: Programming Language :: Python :: 3 :: Only
Classifier: Programming Language :: Python :: 3.10
Classifier: Programming Language :: Python :: 3.11
Classifier: Programming Language :: Python :: 3.12
Classifier: Programming Language :: Python :: 3.7
Classifier: Programming Language :: Python :: 3.8
Classifier: Programming Language :: Python :: 3.9
Classifier: Topic :: Internet
Classifier: Topic :: Internet :: WWW/HTTP
Classifier: Topic :: Software Development :: Libraries
Classifier: Topic :: Software Development :: Libraries :: Python Modules
Classifier: Topic :: Utilities
Requires-Dist: xmltodict (>=0.9.2)
Project-URL: Repository, https://github.com/miigotu/beekeeper
